{"name":"git","permalink":"https://egoist.moe/categories/git/","url":"/async/categories/git.json","count":2,"_total":2,"_totalPage":1,"_page":1,"posts":[{"tags":[{"name":"git","permalink":"https://egoist.moe/tags/git/","url":"/async/tags/git.json","count":2}],"categories":[{"name":"git","permalink":"https://egoist.moe/categories/git/","url":"/async/categories/git.json","count":2}],"url":"/async/posts/2015/10/07/git-memo.json","date":1444223934000,"path":{"year":2015,"month":10,"day":7,"name":"git-memo"},"title":"Git 备忘录","permalink":"https://egoist.moe/2015/10/07/git-memo/","content":""},{"tags":[{"name":"git","permalink":"https://egoist.moe/tags/git/","url":"/async/tags/git.json","count":2},{"name":"udo","permalink":"https://egoist.moe/tags/udo/","url":"/async/tags/udo.json","count":1}],"categories":[{"name":"git","permalink":"https://egoist.moe/categories/git/","url":"/async/categories/git.json","count":2}],"url":"/async/posts/2015/10/04/how-to-undo-with-git.json","date":1443939359000,"path":{"year":2015,"month":10,"day":4,"name":"how-to-undo-with-git"},"title":"如何在 Git 中使用撤消操作","permalink":"https://egoist.moe/2015/10/04/how-to-undo-with-git/","content":""}]}